amrasaman/__init__.py
amrasaman-0.1.5.dist-info/LICENSE
amrasaman-0.1.5.dist-info/METADATA
amrasaman-0.1.5.dist-info/WHEEL
amrasaman-0.1.5.dist-info/entry_points.txt
amrasaman-0.1.5.dist-info/top_level.txt
amrasaman-0.1.5.dist-info/RECORD
