Metadata-Version: 2.1
Name: amrasaman
Version: 0.1.5
Summary: A tool to build reproducible wheels.
Home-page: https://github.com/kushaldas/amrasaman
Author: Kushal Das
Author-email: mail@kushaldas.in
License: UNKNOWN
Platform: UNKNOWN
Classifier: Programming Language :: Python :: 3
Classifier: License :: OSI Approved :: MIT License
Classifier: Operating System :: OS Independent
License-File: LICENSE
Requires-Dist: Click
Requires-Dist: pep517
Requires-Dist: build
Requires-Dist: setuptools
